odoo/addons/l10n_fr_business_document_import/README.rst
odoo/addons/l10n_fr_business_document_import/__init__.py
odoo/addons/l10n_fr_business_document_import/__manifest__.py
odoo/addons/l10n_fr_business_document_import/i18n/l10n_fr_business_document_import.pot
odoo/addons/l10n_fr_business_document_import/models/__init__.py
odoo/addons/l10n_fr_business_document_import/models/business_document_import.py
odoo/addons/l10n_fr_business_document_import/readme/CONTRIBUTORS.rst
odoo/addons/l10n_fr_business_document_import/readme/DESCRIPTION.rst
odoo/addons/l10n_fr_business_document_import/static/description/icon.png
odoo/addons/l10n_fr_business_document_import/static/description/index.html
odoo/addons/l10n_fr_business_document_import/tests/__init__.py
odoo/addons/l10n_fr_business_document_import/tests/test_business_document_import.py
odoo12_addon_l10n_fr_business_document_import-12.0.1.0.2.dist-info/METADATA
odoo12_addon_l10n_fr_business_document_import-12.0.1.0.2.dist-info/WHEEL
odoo12_addon_l10n_fr_business_document_import-12.0.1.0.2.dist-info/top_level.txt
odoo12_addon_l10n_fr_business_document_import-12.0.1.0.2.dist-info/RECORD
