Metadata-Version: 2.1
Name: odoo12-addon-l10n-fr-business-document-import
Version: 12.0.1.0.2
Summary: Adapt the module base_business_document_import for France
Home-page: https://github.com/OCA/l10n-france
Author: Akretion,Odoo Community Association (OCA)
Author-email: support@odoo-community.org
License: AGPL-3
Platform: UNKNOWN
Classifier: Programming Language :: Python
Classifier: Framework :: Odoo
Classifier: License :: OSI Approved :: GNU Affero General Public License v3
Requires-Python: >=3.5
Requires-Dist: odoo12-addon-base-business-document-import
Requires-Dist: odoo12-addon-l10n-fr-siret
Requires-Dist: odoo (<12.1dev,>=12.0a)
